verset/__init__.py
verset-0.1.1.dist-info/METADATA
verset-0.1.1.dist-info/WHEEL
verset-0.1.1.dist-info/entry_points.txt
verset-0.1.1.dist-info/RECORD
