Metadata-Version: 2.1
Name: verset
Version: 0.1.1
Summary: pyprojects.toml dependencies version manager
Home-page: https://github.com/fdev31/verset
License: MIT
Author: fdev31
Author-email: fdev31@gmail.com
Requires-Python: >=3.10,<4.0
Classifier: License :: OSI Approved :: MIT License
Classifier: Programming Language :: Python :: 3
Classifier: Programming Language :: Python :: 3.10
Classifier: Programming Language :: Python :: 3.11
Requires-Dist: tomlkit (>=0.11.7,<0.12.0)
